{
  "id": 4,
  "robots": [
    {"id": "pelta-x", "name": "Pelta X"},
    {"id": "mait", "name": "Mait"}
  ],
  "startingBaskets": ["blue", "magenta"],
  "isTieAllowed": true,
  "hasEnded": false,
  "rounds": [
    {
      "scores": [
        [{"time": 1733420915920, "isValid": true}],
        [
          {"time": 1733420890340, "isValid": true},
          {"time": 1733420902405, "isValid": true},
          {"time": 1733420913152, "isValid": false},
          {"time": 1733420925888, "isValid": true},
          {"time": 1733420925993, "isValid": false},
          {"time": 1733420935715, "isValid": true},
          {"time": 1733420941520, "isValid": true}
        ]
      ],
      "fouls": [[], []],
      "baskets": ["blue", "magenta"],
      "hasEnded": true,
      "isConfirmed": true,
      "roundMaxLength": 60000,
      "runs": [{"startTime": 1733420883860, "endTime": 1733420943921}]
    },
    {
      "scores": [
        [
          {"time": 1733421016675, "isValid": true},
          {"time": 1733421019113, "isValid": true}
        ],
        [
          {"time": 1733421011137, "isValid": true},
          {"time": 1733421017867, "isValid": true},
          {"time": 1733421022374, "isValid": true},
          {"time": 1733421028630, "isValid": true}
        ]
      ],
      "fouls": [[], []],
      "baskets": ["magenta", "blue"],
      "hasEnded": false,
      "isConfirmed": false,
      "roundMaxLength": 60000,
      "runs": [{"startTime": 1733421004293, "endTime": null}]
    }
  ],
  "ballPlacement": [
    [0, 0],
    [-0.12, -0.81],
    [0.12, 0.81],
    [-0.62, -0.62],
    [0.62, 0.62],
    [0.55, -1.11],
    [-0.55, 1.11],
    [0.04, 0.6],
    [-0.04, -0.6],
    [-0.83, 0.51],
    [0.83, -0.51]
  ]
}